consoleplus/__init__.py
consoleplus/out.py
consoleplus-1.1.6.dist-info/METADATA
consoleplus-1.1.6.dist-info/WHEEL
consoleplus-1.1.6.dist-info/top_level.txt
consoleplus-1.1.6.dist-info/RECORD
