Metadata-Version: 2.1
Name: consoleplus
Version: 1.1.6
Summary: Pretty print for Python
Home-page: https://github.com/timof121/ConsolePlus
Author: Evie
License: General Public License v3.0
Keywords: python,console,output,input,pretty,print
